agymc/__init__.py
agymc/src/__init__.py
agymc/src/__main__.py
agymc/src/env.py
agymc/src/exp.py
agymc/src/ref.py
agymc-0.1.1.1.dev0.dist-info/LICENSE
agymc-0.1.1.1.dev0.dist-info/METADATA
agymc-0.1.1.1.dev0.dist-info/WHEEL
agymc-0.1.1.1.dev0.dist-info/top_level.txt
agymc-0.1.1.1.dev0.dist-info/RECORD
