Metadata-Version: 2.1
Name: agymc
Version: 0.1.1.1.dev0
Summary: A concurrent wrapper for OpenAI Gym library that runs multiple environments concurrently.
Home-page: https://github.com/MutatedFlood/agymc
Author: MutatedFlood
Author-email: b06901038@ntu.edu.tw
License: MIT
Platform: UNKNOWN
Classifier: Programming Language :: Python :: 3.7
Requires-Python: >=3.7
Requires-Dist: gym
